EnjoyAnimation/EnjoyAnimation.py
EnjoyAnimation/__init__.py
EnjoyAnimation-0.0.4.dist-info/LICENSE
EnjoyAnimation-0.0.4.dist-info/METADATA
EnjoyAnimation-0.0.4.dist-info/WHEEL
EnjoyAnimation-0.0.4.dist-info/top_level.txt
EnjoyAnimation-0.0.4.dist-info/RECORD
