Metadata-Version: 2.1
Name: EnjoyAnimation
Version: 0.0.4
Summary: 基于nonebot与gocqhttp的动漫番剧插件
Home-page: https://github.com/small-bili/nonebot-plugin-EnjoyAnimation
Author: slexce
Author-email: sim69732@gmail.com
Classifier: Programming Language :: Python :: 3.10
Classifier: License :: OSI Approved :: MIT License
License-File: LICENSE
Requires-Dist: bs4
Requires-Dist: requests
